PySide6FluentUI/__init__.py
PySide6FluentUI/_rc/__init__.py
PySide6FluentUI/_rc/resource.py
PySide6FluentUI/common/__init__.py
PySide6FluentUI/common/animation.py
PySide6FluentUI/common/auto_wrap.py
PySide6FluentUI/common/color.py
PySide6FluentUI/common/config.py
PySide6FluentUI/common/draw_round_rect.py
PySide6FluentUI/common/exception_handler.py
PySide6FluentUI/common/font.py
PySide6FluentUI/common/icon.py
PySide6FluentUI/common/image_utils.py
PySide6FluentUI/common/overload.py
PySide6FluentUI/common/router.py
PySide6FluentUI/common/screen.py
PySide6FluentUI/common/smooth_scroll.py
PySide6FluentUI/common/style_sheet.py
PySide6FluentUI/common/theme_listener.py
PySide6FluentUI/common/translator.py
PySide6FluentUI/components/__init__.py
PySide6FluentUI/components/date_time/__init__.py
PySide6FluentUI/components/date_time/calendar_picker.py
PySide6FluentUI/components/date_time/calendar_view.py
PySide6FluentUI/components/date_time/date_picker.py
PySide6FluentUI/components/date_time/fast_calendar_view.py
PySide6FluentUI/components/date_time/picker_base.py
PySide6FluentUI/components/date_time/time_picker.py
PySide6FluentUI/components/dialog_box/__init__.py
PySide6FluentUI/components/dialog_box/color_dialog.py
PySide6FluentUI/components/dialog_box/dialog.py
PySide6FluentUI/components/dialog_box/folder_list_dialog.py
PySide6FluentUI/components/dialog_box/mask_dialog_base.py
PySide6FluentUI/components/dialog_box/message_box_base.py
PySide6FluentUI/components/dialog_box/message_dialog.py
PySide6FluentUI/components/layout/__init__.py
PySide6FluentUI/components/layout/box_layout.py
PySide6FluentUI/components/layout/expand_layout.py
PySide6FluentUI/components/layout/flow_layout.py
PySide6FluentUI/components/material/__init__.py
PySide6FluentUI/components/material/acrylic_combo_box.py
PySide6FluentUI/components/material/acrylic_flyout.py
PySide6FluentUI/components/material/acrylic_line_edit.py
PySide6FluentUI/components/material/acrylic_menu.py
pyside6_fluent_ui-0.0.5.dist-info/LICENSE
pyside6_fluent_ui-0.0.5.dist-info/METADATA
pyside6_fluent_ui-0.0.5.dist-info/WHEEL
pyside6_fluent_ui-0.0.5.dist-info/top_level.txt
pyside6_fluent_ui-0.0.5.dist-info/RECORD
