Metadata-Version: 2.2
Name: pyside6_fluent_ui
Version: 0.0.5
Summary: A fluent design widgets library based on PySide6
Author: Mikuas
License: GPLv3
License-File: LICENSE
Requires-Dist: PySide6>=6.8.1.1
Requires-Dist: PySide6-Fluent-Widgets[full]>=1.10.4
Requires-Dist: PySideSix-Frameless-Window>=0.7.3
Requires-Dist: pynput>=1.8.1
Dynamic: author
Dynamic: description
Dynamic: description-content-type
Dynamic: license
Dynamic: requires-dist
Dynamic: summary
